{
  "indexes": [
    {
      "collectionGroup": "doctors",
      "queryScope": "COLLECTION",
      "fields": [
        { "fieldPath": "specialty", "order": "ASCENDING" },
        { "fieldPath": "name", "order": "ASCENDING" }
      ]
    },
    {
      "collectionGroup": "appointments",
      "queryScope": "COLLECTION",
      "fields": [
        { "fieldPath": "patient_id", "order": "ASCENDING" },
        { "fieldPath": "datetime", "order": "ASCENDING" }
      ]
    },
    {
      "collectionGroup": "appointments",
      "queryScope": "COLLECTION",
      "fields": [
        { "fieldPath": "doctor_id", "order": "ASCENDING" },
        { "fieldPath": "datetime", "order": "ASCENDING" }
      ]
    }
  ],
  "fieldOverrides": []
}
